{
  "name": "NoGoogle Analytics",
  "description": "This blocklist helps to restrict access to Google and its domains",
  "homepage": "https://github.com/nickspaargaren/no-google",
  "license": "The Unlicense",
  "sources": [
    {
      "name": "https://github.com/nickspaargaren/no-google",
      "source": "https://raw.githubusercontent.com/nickspaargaren/no-google/master/categories/analytics.txt",
      "type": "hosts",
      "transformations": ["Compress", "Validate"]
    }
  ],
  "transformations": ["Deduplicate", "RemoveEmptyLines", "InsertFinalNewLine"]
}